<?xml version="1.0" encoding="utf-8"?>
<!DOCTYPE hibernate-mapping PUBLIC "-//Hibernate/Hibernate Mapping DTD 3.0//EN"
"http://hibernate.sourceforge.net/hibernate-mapping-3.0.dtd">
<!-- 
    Mapping file autogenerated by MyEclipse Persistence Tools
-->
<hibernate-mapping>
    <class name="com.bbs.vo.MainTitle" table="MainTitle" schema="EightZeroBBS">
        <id name="mid" type="int">
            <generator class="native"/>
        </id>
        <property name="mtitle" type="string">
            <column name="mtitle"  />
        </property>
        <property name="mcontent" type="string">
            <column name="mcontent"  />
        </property>
        <property name="mtime" type="date">
            <column name="mtime"  />
        </property>
         <many-to-one name="userinfo" class="com.bbs.vo.Userinfo" >
            <column name="uid"/>
        </many-to-one>
        <property name="mThing" type="string">
            <column name="mThing"  />
        </property>
     	<many-to-one name="sonBorad" class="com.bbs.vo.SonBorad">
     		<column name="sid"/>
     	</many-to-one>
         <property name="mstatus" type="int">
            <column name="mstatus"  />
        </property>
        <set name="replay">
        	<key>
        		<column name="rid"/>
        	</key>
        	<one-to-many class="com.bbs.vo.Replay"/>
        </set>
    </class>
</hibernate-mapping>
